Workbook

Sheet Dashboard
A1: FREELANCER BUSINESS DASHBOARD
A2: Your business at a glance | Data updates automatically from other tabs
A4: KEY METRICS
A5: Total Revenue (YTD) | C5: Outstanding Invoices | E5: Active Projects | G5: Monthly Avg Income
A6: ='Income & Expenses'!E12 | C6: =SUMIF('Invoice Tracker'!G:G,"Sent",'Invoice Tracker'!F:F) | E6: =COUNTIF('Project Pipeline'!C:C,"Active") | G6: ='Income & Expenses'!E12/MONTH(TODAY())
A8: QUICK STATS | F8: MONTHLY REVENUE
A9: Total Clients: | B9: =COUNTA('Client CRM'!A2:A200) | F9: Month | G9: Income | H9: Expenses
A10: Active Clients: | B10: =COUNTIF('Client CRM'!G:G,"Active") | F10: January | G10: =SUMPRODUCT(('Income & Expenses'!A3:A10<>"")*(MONTH('Income & Expenses'!A3:A10)=1)*('Income & Expenses'!E3:E10)) | H10: =SUMPRODUCT(('Income & Expenses'!A16:A25<>"")*(MONTH('Income & Expenses'!A16:A25)=1)*('Income & Expenses'!D16:D25))
A11: Avg Project Value: | B11: =AVERAGE('Project Pipeline'!I2:I200) | F11: February | G11: =SUMPRODUCT(('Income & Expenses'!A3:A10<>"")*(MONTH('Income & Expenses'!A3:A10)=2)*('Income & Expenses'!E3:E10)) | H11: =SUMPRODUCT(('Income & Expenses'!A16:A25<>"")*(MONTH('Income & Expenses'!A16:A25)=2)*('Income & Expenses'!D16:D25))
A12: Total Expenses (YTD): | B12: ='Income & Expenses'!D26 | F12: March | G12: =SUMPRODUCT(('Income & Expenses'!A3:A10<>"")*(MONTH('Income & Expenses'!A3:A10)=3)*('Income & Expenses'!E3:E10)) | H12: =SUMPRODUCT(('Income & Expenses'!A16:A25<>"")*(MONTH('Income & Expenses'!A16:A25)=3)*('Income & Expenses'!D16:D25))
A13: Net Profit (YTD): | B13: ='Income & Expenses'!B32 | F13: April | G13: =SUMPRODUCT(('Income & Expenses'!A3:A10<>"")*(MONTH('Income & Expenses'!A3:A10)=4)*('Income & Expenses'!E3:E10)) | H13: =SUMPRODUCT(('Income & Expenses'!A16:A25<>"")*(MONTH('Income & Expenses'!A16:A25)=4)*('Income & Expenses'!D16:D25))
A14: Profit Margin: | B14: =IF('Income & Expenses'!B30>0,'Income & Expenses'!B32/'Income & Expenses'!B30,0) | F14: May | G14: =SUMPRODUCT(('Income & Expenses'!A3:A10<>"")*(MONTH('Income & Expenses'!A3:A10)=5)*('Income & Expenses'!E3:E10)) | H14: =SUMPRODUCT(('Income & Expenses'!A16:A25<>"")*(MONTH('Income & Expenses'!A16:A25)=5)*('Income & Expenses'!D16:D25))
F15: June | G15: =SUMPRODUCT(('Income & Expenses'!A3:A10<>"")*(MONTH('Income & Expenses'!A3:A10)=6)*('Income & Expenses'!E3:E10)) | H15: =SUMPRODUCT(('Income & Expenses'!A16:A25<>"")*(MONTH('Income & Expenses'!A16:A25)=6)*('Income & Expenses'!D16:D25))
A16: PIPELINE STATUS | F16: July | G16: =SUMPRODUCT(('Income & Expenses'!A3:A10<>"")*(MONTH('Income & Expenses'!A3:A10)=7)*('Income & Expenses'!E3:E10)) | H16: =SUMPRODUCT(('Income & Expenses'!A16:A25<>"")*(MONTH('Income & Expenses'!A16:A25)=7)*('Income & Expenses'!D16:D25))
A17: Lead | B17: =COUNTIF('Project Pipeline'!C:C,"Lead") | C17: =SUMIF('Project Pipeline'!C:C,"Lead",'Project Pipeline'!I:I) | F17: August | G17: =SUMPRODUCT(('Income & Expenses'!A3:A10<>"")*(MONTH('Income & Expenses'!A3:A10)=8)*('Income & Expenses'!E3:E10)) | H17: =SUMPRODUCT(('Income & Expenses'!A16:A25<>"")*(MONTH('Income & Expenses'!A16:A25)=8)*('Income & Expenses'!D16:D25))
A18: Proposal | B18: =COUNTIF('Project Pipeline'!C:C,"Proposal") | C18: =SUMIF('Project Pipeline'!C:C,"Proposal",'Project Pipeline'!I:I) | F18: September | G18: =SUMPRODUCT(('Income & Expenses'!A3:A10<>"")*(MONTH('Income & Expenses'!A3:A10)=9)*('Income & Expenses'!E3:E10)) | H18: =SUMPRODUCT(('Income & Expenses'!A16:A25<>"")*(MONTH('Income & Expenses'!A16:A25)=9)*('Income & Expenses'!D16:D25))
A19: Active | B19: =COUNTIF('Project Pipeline'!C:C,"Active") | C19: =SUMIF('Project Pipeline'!C:C,"Active",'Project Pipeline'!I:I) | F19: October | G19: =SUMPRODUCT(('Income & Expenses'!A3:A10<>"")*(MONTH('Income & Expenses'!A3:A10)=10)*('Income & Expenses'!E3:E10)) | H19: =SUMPRODUCT(('Income & Expenses'!A16:A25<>"")*(MONTH('Income & Expenses'!A16:A25)=10)*('Income & Expenses'!D16:D25))
A20: Review | B20: =COUNTIF('Project Pipeline'!C:C,"Review") | C20: =SUMIF('Project Pipeline'!C:C,"Review",'Project Pipeline'!I:I) | F20: November | G20: =SUMPRODUCT(('Income & Expenses'!A3:A10<>"")*(MONTH('Income & Expenses'!A3:A10)=11)*('Income & Expenses'!E3:E10)) | H20: =SUMPRODUCT(('Income & Expenses'!A16:A25<>"")*(MONTH('Income & Expenses'!A16:A25)=11)*('Income & Expenses'!D16:D25))
A21: Complete | B21: =COUNTIF('Project Pipeline'!C:C,"Complete") | C21: =SUMIF('Project Pipeline'!C:C,"Complete",'Project Pipeline'!I:I) | F21: December | G21: =SUMPRODUCT(('Income & Expenses'!A3:A10<>"")*(MONTH('Income & Expenses'!A3:A10)=12)*('Income & Expenses'!E3:E10)) | H21: =SUMPRODUCT(('Income & Expenses'!A16:A25<>"")*(MONTH('Income & Expenses'!A16:A25)=12)*('Income & Expenses'!D16:D25))
A23: INVOICE SUMMARY
A24: Paid | B24: =COUNTIF('Invoice Tracker'!G:G,"Paid") | C24: =SUMIF('Invoice Tracker'!G:G,"Paid",'Invoice Tracker'!F:F)
A25: Sent | B25: =COUNTIF('Invoice Tracker'!G:G,"Sent") | C25: =SUMIF('Invoice Tracker'!G:G,"Sent",'Invoice Tracker'!F:F)
A26: Overdue | B26: =COUNTIF('Invoice Tracker'!G:G,"Overdue") | C26: =SUMIF('Invoice Tracker'!G:G,"Overdue",'Invoice Tracker'!F:F)
A27: Draft | B27: =COUNTIF('Invoice Tracker'!G:G,"Draft") | C27: =SUMIF('Invoice Tracker'!G:G,"Draft",'Invoice Tracker'!F:F)

Sheet Client CRM
A1: Client Name | B1: Company | C1: Email | D1: Phone | E1: Industry | F1: Source | G1: Status | H1: First Contact | I1: Last Contact | J1: Lifetime Value | K1: Notes | L1: Next Follow-up
A2: Sarah Mitchell | B2: BrightPath Marketing | C2: sarah@brightpath.co | D2: (555) 234-8901 | E2: Marketing | F2: Referral | G2: Active | H2: 2025-03-15 | I2: 2026-02-28 | J2: =SUMIFS('Project Pipeline'!I:I,'Project Pipeline'!B:B,A2) | K2: Great communicator, prefers Slack | L2: 2026-03-20
A3: David Chen | B3: Chen Legal Group | C3: david@chenlegal.com | D3: (555) 456-7890 | E3: Legal | F3: Website | G3: Active | H3: 2025-06-01 | I3: 2026-03-10 | J3: =SUMIFS('Project Pipeline'!I:I,'Project Pipeline'!B:B,A3) | K3: Needs quick turnaround, pays on time | L3: 2026-04-01
A4: Maria Rodriguez | B4: Bloom & Grow Cafe | C4: maria@bloomgrow.com | D4: (555) 789-0123 | E4: Food & Bev | F4: Social Media | G4: Lead | H4: 2026-02-14 | I4: 2026-03-01 | J4: =SUMIFS('Project Pipeline'!I:I,'Project Pipeline'!B:B,A4) | K4: Interested in brand redesign, follow up Q2 | L4: 2026-03-25

Sheet Project Pipeline
A1: Project Name | B1: Client | C1: Status | D1: Start Date | E1: Deadline | F1: Est. Hours | G1: Actual Hours | H1: Hourly Rate | I1: Project Value | J1: Amount Paid | K1: Amount Due | L1: Priority | M1: Notes
A2: Website Redesign | B2: Sarah Mitchell | C2: Active | D2: 2026-01-15 | E2: 2026-04-15 | F2: 80 | G2: 45 | H2: 95 | I2: =F2*H2 | J2: 3800 | K2: =I2-J2 | L2: High | M2: Phase 2 starting next week
A3: Brand Identity Package | B3: Maria Rodriguez | C3: Proposal | D3: 2026-04-01 | E3: 2026-05-30 | F3: 40 | G3: 0 | H3: 85 | I3: =F3*H3 | J3: 0 | K3: =I3-J3 | L3: Medium | M3: Waiting on client approval
A4: Legal Blog Content | B4: David Chen | C4: Active | D4: 2026-02-01 | E4: 2026-06-30 | F4: 120 | G4: 68 | H4: 75 | I4: =F4*H4 | J4: 4500 | K4: =I4-J4 | L4: Medium | M4: Monthly retainer - 10 posts/mo
A5: Email Campaign Setup | B5: Sarah Mitchell | C5: Complete | D5: 2025-10-01 | E5: 2025-12-15 | F5: 30 | G5: 28 | H5: 95 | I5: =F5*H5 | J5: 2660 | K5: =I5-J5 | L5: Low | M5: Delivered on time, client happy

Sheet Invoice Tracker
A1: Invoice # | B1: Client | C1: Project | D1: Date Sent | E1: Due Date | F1: Amount | G1: Status | H1: Payment Date | I1: Payment Method | J1: Days to Pay | K1: Late Fee | L1: Notes
A2: INV-2026-001 | B2: Sarah Mitchell | C2: Website Redesign | D2: 2026-01-20 | E2: 2026-02-19 | F2: 3800 | G2: Paid | H2: 2026-02-15 | I2: Bank Transfer | J2: =IF(H2<>"",H2-D2,IF(G2="Paid","",TODAY()-D2)) | K2: 0 | L2: Deposit - 50%
A3: INV-2026-002 | B3: David Chen | C3: Legal Blog Content | D3: 2026-02-01 | E3: 2026-03-03 | F3: 2250 | G3: Paid | H3: 2026-03-01 | I3: PayPal | J3: =IF(H3<>"",H3-D3,IF(G3="Paid","",TODAY()-D3)) | K3: 0 | L3: Feb retainer
A4: INV-2026-003 | B4: David Chen | C4: Legal Blog Content | D4: 2026-03-01 | E4: 2026-03-31 | F4: 2250 | G4: Sent | J4: =IF(H4<>"",H4-D4,IF(G4="Paid","",TODAY()-D4)) | K4: 0 | L4: Mar retainer
A5: INV-2026-004 | B5: Sarah Mitchell | C5: Website Redesign | D5: 2026-03-15 | E5: 2026-04-14 | F5: 3800 | G5: Sent | J5: =IF(H5<>"",H5-D5,IF(G5="Paid","",TODAY()-D5)) | K5: 0 | L5: Final 50%
A6: INV-2026-005 | B6: Sarah Mitchell | C6: Email Campaign Setup | D6: 2025-12-18 | E6: 2026-01-17 | F6: 2660 | G6: Paid | H6: 2026-01-20 | I6: Stripe | J6: =IF(H6<>"",H6-D6,IF(G6="Paid","",TODAY()-D6)) | K6: 0 | L6: Final payment
A8: SUMMARY
A9: Total Invoiced: | B9: =SUM(F2:F6)
A10: Total Paid: | B10: =SUMIF(G2:G6,"Paid",F2:F6)
A11: Total Outstanding: | B11: =SUMIF(G2:G6,"Sent",F2:F6)
A12: Total Overdue: | B12: =SUMIF(G2:G6,"Overdue",F2:F6)

Sheet Income & Expenses
A1: INCOME
A2: Date | B2: Client | C2: Project | D2: Category | E2: Amount | F2: Payment Method | G2: Tax Deductible
A3: 2026-01-15 | B3: Sarah Mitchell | C3: Website Redesign | D3: Freelance | E3: 3800 | F3: Bank Transfer | G3: No
A4: 2026-01-20 | B4: David Chen | C4: Legal Blog Content | D4: Retainer | E4: 2250 | F4: PayPal | G4: No
A5: 2026-02-01 | C5: Online Course Sales | D5: Passive | E5: 340 | F5: Stripe | G5: No
A6: 2026-02-15 | B6: David Chen | C6: Legal Blog Content | D6: Retainer | E6: 2250 | F6: PayPal | G6: No
A7: 2026-02-20 | B7: Sarah Mitchell | C7: Email Campaign Setup | D7: Freelance | E7: 2660 | F7: Stripe | G7: No
A8: 2026-03-01 | C8: Online Course Sales | D8: Passive | E8: 415 | F8: Stripe | G8: No
A9: 2026-03-05 | B9: David Chen | C9: Legal Blog Content | D9: Retainer | E9: 2250 | F9: PayPal | G9: No
A10: 2026-03-10 | B10: Maria Rodriguez | C10: Brand Consultation | D10: Consultation | E10: 250 | F10: Venmo | G10: No
D12: Total Income: | E12: =SUM(E3:E10)
A14: EXPENSES
A15: Date | B15: Vendor | C15: Category | D15: Amount | E15: Tax Deductible | F15: Receipt | G15: Notes
A16: 2026-01-05 | B16: Adobe | C16: Software | D16: 54.99 | E16: Yes | F16: Yes | G16: Creative Cloud monthly
A17: 2026-01-05 | B17: Notion | C17: Software | D17: 10 | E17: Yes | F17: Yes | G17: Workspace Pro
A18: 2026-01-10 | B18: WeWork | C18: Office | D18: 350 | E18: Yes | F18: Yes | G18: Hot desk membership
A19: 2026-01-15 | B19: Google Ads | C19: Marketing | D19: 150 | E19: Yes | F19: Yes | G19: Portfolio promotion
A20: 2026-02-01 | B20: Udemy | C20: Education | D20: 89.99 | E20: Yes | F20: Yes | G20: Advanced UX course
A21: 2026-02-05 | B21: Adobe | C21: Software | D21: 54.99 | E21: Yes | F21: Yes | G21: Creative Cloud monthly
A22: 2026-02-10 | B22: WeWork | C22: Office | D22: 350 | E22: Yes | F22: Yes | G22: Hot desk membership
A23: 2026-02-20 | B23: Delta Airlines | C23: Travel | D23: 380 | E23: Yes | F23: Yes | G23: Client meeting - NYC
A24: 2026-03-01 | B24: Professional Liability Ins. | C24: Insurance | D24: 125 | E24: Yes | F24: Yes | G24: Monthly premium
A25: 2026-03-05 | B25: Adobe | C25: Software | D25: 54.99 | E25: Yes | F25: Yes | G25: Creative Cloud monthly
C26: Total Expenses: | D26: =SUM(D16:D25)
C27: Tax Deductible: | D27: =SUMIF(E16:E25,"Yes",D16:D25)
A29: PROFIT / LOSS
A30: Total Income: | B30: =E12
A31: Total Expenses: | B31: =D26
A32: Net Profit: | B32: =B30-B31

Sheet Rate Calculator
A1: FREELANCE RATE CALCULATOR
A3: YOUR INPUTS
A4: Desired Annual Income | C4: 75000
A5: Working Weeks / Year | C5: 48
A6: Billable Hours / Week | C6: 30
A7: Annual Business Expenses | C7: 12000
A8: Tax Rate | C8: 0.25
A9: Desired Profit Margin | C9: 0.15
A12: CALCULATED RATES
A13: Required Revenue (pre-tax) | C13: =(C4+C7)/(1-C8)
A14: Billable Hours / Year | C14: =C5*C6
A15: Minimum Hourly Rate | C15: =C13/C14
A16: Suggested Hourly Rate (with margin) | C16: =C15*(1+C9)
A17: Day Rate (8 hrs) | C17: =C16*8
A18: Weekly Rate | C18: =C16*C6
A19: Monthly Retainer Rate | C19: =C16*C6*4.33
A22: RATE COMPARISON BY UTILIZATION
A23: Utilization Rate | B23: Billable Hours/Year | C23: Hourly Rate | D23: Day Rate | E23: Weekly Rate | F23: Monthly Retainer
A24: 0.6 | B24: =C5*C6*A24 | C24: =C13/B24 | D24: =C24*8 | E24: =C24*C6 | F24: =C24*C6*4.33
A25: 0.7 | B25: =C5*C6*A25 | C25: =C13/B25 | D25: =C25*8 | E25: =C25*C6 | F25: =C25*C6*4.33
A26: 0.8 | B26: =C5*C6*A26 | C26: =C13/B26 | D26: =C26*8 | E26: =C26*C6 | F26: =C26*C6*4.33
A27: 0.9 | B27: =C5*C6*A27 | C27: =C13/B27 | D27: =C27*8 | E27: =C27*C6 | F27: =C27*C6*4.33
A30: WHAT-IF SCENARIOS
A31: If I raise my rate by: | C31: 10
A32: New hourly rate: | C32: =C16+C31
A33: Additional annual income: | C33: =C31*C14
A34: New annual revenue: | C34: =C32*C14

Sheet Proposal Template
A1: [YOUR COMPANY NAME]
A2: [your@email.com] | [yourwebsite.com] | [(555) 000-0000]
A4: PROJECT PROPOSAL
A6: PREPARED FOR: | D6: PROJECT DETAILS:
A7: Client Name: | B7: Sarah Mitchell | D7: Project: | E7: Website Redesign
A8: Company: | B8: BrightPath Marketing | D8: Timeline: | E8: 8-10 weeks
A9: Date: | B9: March 17, 2026 | D9: Proposal #: | E9: PROP-2026-007
A10: Valid Until: | B10: April 17, 2026
A12: PROJECT OVERVIEW
A13: A complete redesign of the BrightPath Marketing website to improve user experience, modernize the visual design, and optimize for lead generation. The project includes responsive design, SEO optimization, and integration with existing marketing tools.
A17: SCOPE OF WORK
A18: # | B18: Deliverable | C18: Description | D18: Timeline | E18: Price
A19: 1 | B19: Discovery & Research | C19: Stakeholder interviews, competitor analysis, user research | D19: Week 1-2 | E19: 1200
A20: 2 | B20: Wireframes & Prototypes | C20: Low-fi wireframes, interactive prototype, client review | D20: Week 3-4 | E20: 1800
A21: 3 | B21: Visual Design | C21: High-fidelity mockups for all pages, style guide | D21: Week 5-6 | E21: 2400
A22: 4 | B22: Development | C22: Responsive HTML/CSS/JS build, CMS integration | D22: Week 7-9 | E22: 3200
A23: 5 | B23: Testing & Launch | C23: QA testing, bug fixes, deployment, training | D23: Week 10 | E23: 1000
D24: TOTAL: | E24: =SUM(E19:E23)
A26: PAYMENT TERMS
A27: 1. | B27: 50% deposit required before work begins
A28: 2. | B28: 25% due upon design approval (after Phase 3)
A29: 3. | B29: 25% due upon project completion and delivery
A30: 4. | B30: Payment due within 15 days of invoice date
A31: 5. | B31: Late payments subject to 1.5% monthly interest
A33: TERMS & CONDITIONS
A34: 1. | B34: This proposal is valid for 30 days from the date above.
A35: 2. | B35: Project timeline begins upon receipt of signed agreement and deposit.
A36: 3. | B36: Up to 2 rounds of revisions are included per deliverable phase.
A37: 4. | B37: Additional revisions will be billed at the agreed hourly rate.
A38: 5. | B38: Client is responsible for providing all required content and assets on time.
A39: 6. | B39: Delays in client feedback may extend the project timeline.
A42: ACCEPTED BY: | D42: PREPARED BY:
A43: Signature: ___________________________ | D43: Signature: ___________________________
A44: Date: ___________________________ | D44: Date: ___________________________
